classic_CandidateElimination/__init__.py
classic_CandidateElimination-2.0.0.dist-info/LICENSE
classic_CandidateElimination-2.0.0.dist-info/METADATA
classic_CandidateElimination-2.0.0.dist-info/WHEEL
classic_CandidateElimination-2.0.0.dist-info/top_level.txt
classic_CandidateElimination-2.0.0.dist-info/RECORD
