Metadata-Version: 2.1
Name: classic-CandidateElimination
Version: 2.0.0
Summary: Candidate-Elimination Algorithm is a Machine Learning Algorithm that builds the version space from Specific Hypothesis and General Hypothesis.
Home-page: https://github.com/safir72347/ML-CandidateElimination-PyPi
Author: Safir Motiwala
Author-email: safirmotiwala@gmail.com
License: UNKNOWN
Platform: UNKNOWN
Classifier: Programming Language :: Python :: 3
Classifier: License :: OSI Approved :: MIT License
Classifier: Operating System :: OS Independent
Requires-Python: >=3.0
